localify/__init__.py
localify/core.py
localify/loaders.py
localify/localify.py
localify/translation.py
tests/__init__.py
tests/test_localify.py
localify-0.1.0.dist-info/LICENSE
localify-0.1.0.dist-info/METADATA
localify-0.1.0.dist-info/WHEEL
localify-0.1.0.dist-info/top_level.txt
localify-0.1.0.dist-info/RECORD
