Metadata-Version: 2.1
Name: localify
Version: 0.1.0
Summary: A lightweight i18n localization package for Python
Home-page: https://github.com/felicedev/localify
Author: FeliceDev
Author-email: felicedev@outlook.com
Classifier: Programming Language :: Python :: 3
Classifier: License :: OSI Approved :: MIT License
Classifier: Operating System :: OS Independent
Requires-Python: >=3.6
License-File: LICENSE
Provides-Extra: yaml
Requires-Dist: pyyaml; extra == "yaml"
